{
  "$schema": "https://raw.githubusercontent.com/getmanfred/mac/v0.3/schema/schema.json",
  "settings": {
    "language": "ES",
    "MACVersion": "0.3"
  },
  "aboutMe": {
    "profile": {
      "name": "Manuel Trinidad",
      "surnames": "Cerezo Bonilla",
      "title": "Frontend developer at WebCargo by Freightos",
      "description": "",
      "avatar": {
        "alt": "rExzsi5B_400x400.jpeg",
        "link": "https://media-asgard.s3.eu-west-1.amazonaws.com/22/09/14/70273a40-707c-4594-8cb4-fb6785a909a6_rexzsi5b_400x400.jpeg"
      },
      "location": {
        "country": "España",
        "region": "Cataluña",
        "municipality": "Barcelona",
        "notes": "Autocompleted using Google Maps API"
      }
    },
    "relevantLinks": [
      {
        "type": "twitter",
        "URL": "https://twitter.com/manuelizo_"
      },
      {
        "type": "linkedin",
        "URL": "https://www.linkedin.com/in/manuel-cerezo/"
      }
    ]
  },
  "knowledge": {
    "languages": [
      {
        "name": "English",
        "level": "Full professional proficiency"
      },
      {
        "name": "Spanish",
        "level": "Native or bilingual proficiency"
      }
    ],
    "hardSkills": [
      {
        "skill": {
          "name": "CSS",
          "type": "technology"
        }
      },
      {
        "skill": {
          "name": "JavaScript",
          "type": "technology"
        }
      },
      {
        "skill": {
          "name": "HTML",
          "type": "technology"
        }
      },
      {
        "skill": {
          "name": "jQuery",
          "type": "technology"
        }
      },
      {
        "skill": {
          "name": "Sass",
          "type": "technology"
        }
      },
      {
        "skill": {
          "name": "React",
          "type": "technology"
        }
      },
      {
        "skill": {
          "name": "StyledComponents",
          "type": "technology"
        }
      },
      {
        "skill": {
          "name": "TypeScript",
          "type": "technology"
        }
      }
    ]
  },
  "careerPreferences": {
    "contact": {
      "publicProfiles": [
        {
          "type": "linkedin",
          "URL": "https://www.linkedin.com/in/manuel-cerezo/"
        }
      ]
    },
    "preferences": {
      "preferredRoles": [
        "Frontend Developer"
      ]
    },
    "status": "searchingActively"
  }
}